{
  "barrel_distortion": {
    "k1": 0.3,
    "k2": 0.35
  },
  "camera_params": {
    "fov_x": 40.0,
    "fov_y": 23.14091682434082,
    "fx": 2637.5783226764374,
    "fy": 2637.5783597197296,
    "cx": 960.0,
    "cy": 540.0
  },
  "points_3d": [
    [
      -1.03,
      -2.22,
      2.4
    ],
    [
      -1.03,
      2.4,
      2.4
    ],
    [
      1.045,
      2.4,
      2.4
    ],
    [
      1.045,
      -2.22,
      2.4
    ]
  ],
  "points_2d_original": [
    {
      "x": 1278.345651626587,
      "y": 385.86075961589813
    },
    {
      "x": 1145.4506492614746,
      "y": 657.6946985721588
    },
    {
      "x": 820.5504083633423,
      "y": 614.7064304351807
    },
    {
      "x": 1013.7597906589508,
      "y": 358.2576584815979
    }
  ],
  "points_2d": [
    {
      "x": 1458.8209377199228,
      "y": 298.75820671101786
    },
    {
      "x": 1273.8116863249252,
      "y": 742.4103515509616
    },
    {
      "x": 716.4717925588941,
      "y": 672.3596943204789
    },
    {
      "x": 1051.5483915275513,
      "y": 227.8880078954863
    }
  ],
  "distances_to_camera": [
    20.149188471214714,
    16.006523240902276,
    16.50529932235998,
    20.54764987797106
  ],
  "target_volume": 10,
  "texture_diffuse": "textures/stones_8k/rocks_ground_01_diff_8k.jpg",
  "transform_params": {
    "crop": {
      "left": 423,
      "top": 238,
      "right": 1498,
      "bottom": 840
    },
    "resize": {
      "target_width": 1920,
      "target_height": 1080
    },
    "original_image_size": {
      "width": 1920,
      "height": 1080
    }
  }
}